graw/__init__.py
graw/github.py
graw/gitlab.py
graw/graw.py
graw-0.0.0.dist-info/LICENSE
graw-0.0.0.dist-info/METADATA
graw-0.0.0.dist-info/WHEEL
graw-0.0.0.dist-info/entry_points.txt
graw-0.0.0.dist-info/top_level.txt
graw-0.0.0.dist-info/RECORD
