Metadata-Version: 2.1
Name: graw
Version: 0.0.0
Summary: Dowload files and subdirectories from github.com and gitlab.com
Home-page: https://github.com/iamsajjad/graw
Author: Sajjad alDalwachee
Author-email: sajjad.alDalwachee@gmail.com
License: MIT
Platform: UNKNOWN
Classifier: License :: OSI Approved :: MIT License
Classifier: Programming Language :: Python :: 3.7
Classifier: Programming Language :: Python :: 3.8
Classifier: Programming Language :: Python :: 3.9
License-File: LICENSE
Requires-Dist: requests
